synctogit
