Metadata-Version: 1.1
Name: synctogit
Version: 2.0.0
Summary: Syncs Evernote(R) notes to a git repository in HTML.
Home-page: https://github.com/KostyaEsmukov/SyncToGit
Author: Kostya Esmukov
Author-email: kostya@esmukov.ru
License: MIT
Keywords: evernote backup git
Platform: UNKNOWN
Classifier: Development Status :: 4 - Beta
Classifier: License :: OSI Approved :: MIT License
Classifier: Natural Language :: English
Classifier: Operating System :: OS Independent
Classifier: Programming Language :: Python :: 2.7
Classifier: Topic :: Utilities
